chicken_turtle_util/__init__.py
chicken_turtle_util/algorithms.py
chicken_turtle_util/asyncio.py
chicken_turtle_util/click.py
chicken_turtle_util/configuration.py
chicken_turtle_util/data_frame.py
chicken_turtle_util/debug.py
chicken_turtle_util/dict.py
chicken_turtle_util/exceptions.py
chicken_turtle_util/function.py
chicken_turtle_util/hashlib.py
chicken_turtle_util/http.py
chicken_turtle_util/inspect.py
chicken_turtle_util/iterable.py
chicken_turtle_util/logging.py
chicken_turtle_util/multi_dict.py
chicken_turtle_util/observable.py
chicken_turtle_util/path.py
chicken_turtle_util/pymysql.py
chicken_turtle_util/series.py
chicken_turtle_util/set.py
chicken_turtle_util/sqlalchemy.py
chicken_turtle_util/test.py
chicken_turtle_util/tests/__init__.py
chicken_turtle_util/tests/conftest.py
chicken_turtle_util/tests/test_algorithms.py
chicken_turtle_util/tests/test_asyncio.py
chicken_turtle_util/tests/test_click.py
chicken_turtle_util/tests/test_configuration.py
chicken_turtle_util/tests/test_data_frame.py
chicken_turtle_util/tests/test_debug.py
chicken_turtle_util/tests/test_dict.py
chicken_turtle_util/tests/test_function.py
chicken_turtle_util/tests/test_hashlib.py
chicken_turtle_util/tests/test_http.py
chicken_turtle_util/tests/test_inspect.py
chicken_turtle_util/tests/test_iterable.py
chicken_turtle_util/tests/test_logging.py
chicken_turtle_util/tests/test_multi_dict.py
chicken_turtle_util/tests/test_observable.py
chicken_turtle_util/tests/test_path.py
chicken_turtle_util/tests/test_series.py
chicken_turtle_util/tests/test_set.py
chicken_turtle_util/tests/test_sqlalchemy.py
chicken_turtle_util-4.1.2.dist-info/DESCRIPTION.rst
chicken_turtle_util-4.1.2.dist-info/METADATA
chicken_turtle_util-4.1.2.dist-info/RECORD
chicken_turtle_util-4.1.2.dist-info/WHEEL
chicken_turtle_util-4.1.2.dist-info/metadata.json
chicken_turtle_util-4.1.2.dist-info/top_level.txt
